pyvolleydata/__init__.py
pyvolleydata/get_data.py
pyvolleydata/helpers.py
pyvolleydata-1.0.0.dist-info/licenses/LICENSE
pyvolleydata-1.0.0.dist-info/METADATA
pyvolleydata-1.0.0.dist-info/WHEEL
pyvolleydata-1.0.0.dist-info/RECORD
