Metadata-Version: 2.4
Name: pyvolleydata
Version: 1.0.0
Summary: Extract and analyze volleyball data from the pvf and lovb volleyball leagues.
License: MIT
License-File: LICENSE
Author: Ryan Du
Requires-Python: >=3.12,<4.0
Classifier: License :: OSI Approved :: MIT License
Classifier: Programming Language :: Python :: 3
Classifier: Programming Language :: Python :: 3.12
Classifier: Programming Language :: Python :: 3.13
Classifier: Programming Language :: Python :: 3.14
Requires-Dist: pandas (>=2.3.1,<3.0.0)
Project-URL: Documentation, https://pyvolleydata.readthedocs.io/en/latest/index.html
